casingSimulations/__init__.py
casingSimulations/base.py
casingSimulations/info.py
casingSimulations/mesh.py
casingSimulations/model.py
casingSimulations/physics.py
casingSimulations/run.py
casingSimulations/sources.py
casingSimulations/utils.py
casingSimulations/view.py
tests/__init__.py
tests/test_SimulationRun.py
tests/test_cyl2D3D.py
tests/test_meshGenerators.py
tests/test_model.py
CasingSimulations-0.2.1.dist-info/LICENSE
CasingSimulations-0.2.1.dist-info/METADATA
CasingSimulations-0.2.1.dist-info/WHEEL
CasingSimulations-0.2.1.dist-info/top_level.txt
CasingSimulations-0.2.1.dist-info/RECORD
