Metadata-Version: 2.1
Name: CasingSimulations
Version: 0.2.1
Summary: Casing Simulations: Electromagnetics + Steel Cased Wells
Home-page: http://github.com/simpeg-research/casingResearch
Download-URL: http://github.com/simpeg-research/casingResearch
Author: Lindsey Heagy
Author-email: lindseyheagy@gmail.com
License: MIT
Keywords: geophysics electromagnetics
Platform: Windows
Platform: Linux
Platform: Solaris
Platform: Mac OS-X
Platform: Unix
Classifier: Development Status :: 4 - Beta
Classifier: Intended Audience :: Developers
Classifier: Intended Audience :: Science/Research
Classifier: License :: OSI Approved :: MIT License
Classifier: Programming Language :: Python
Classifier: Topic :: Scientific/Engineering
Classifier: Topic :: Scientific/Engineering :: Mathematics
Classifier: Topic :: Scientific/Engineering :: Physics
Classifier: Operating System :: Microsoft :: Windows
Classifier: Operating System :: POSIX
Classifier: Operating System :: Unix
Classifier: Operating System :: MacOS
Classifier: Natural Language :: English
License-File: LICENSE
Requires-Dist: numpy (>=1.7)
Requires-Dist: scipy (>=0.13)
Requires-Dist: cython
Requires-Dist: pymatsolver (>=0.1.1)
Requires-Dist: ipywidgets
Requires-Dist: jupyter
Requires-Dist: matplotlib
Requires-Dist: properties
Requires-Dist: vectormath
Requires-Dist: SimPEG
